[
  {
    "combo": "T1",
    "tier": "T1",
    "mod": "",
    "n_picks": 2778,
    "win5d": 40.82,
    "avg_ret5d": -0.267,
    "win10d": 40.24,
    "avg_ret10d": -0.03,
    "med_ret5d": -1.028,
    "med_ret10d": -1.593
  },
  {
    "combo": "T1+e",
    "tier": "T1",
    "mod": "e",
    "n_picks": 2474,
    "win5d": 40.74,
    "avg_ret5d": -0.258,
    "win10d": 40.34,
    "avg_ret10d": 0.013,
    "med_ret5d": -1.002,
    "med_ret10d": -1.471
  },
  {
    "combo": "T1+k",
    "tier": "T1",
    "mod": "k",
    "n_picks": 2508,
    "win5d": 40.71,
    "avg_ret5d": -0.227,
    "win10d": 39.95,
    "avg_ret10d": -0.066,
    "med_ret5d": -0.98,
    "med_ret10d": -1.593
  },
  {
    "combo": "T1+ek",
    "tier": "T1",
    "mod": "ek",
    "n_picks": 2294,
    "win5d": 40.58,
    "avg_ret5d": -0.204,
    "win10d": 39.93,
    "avg_ret10d": -0.026,
    "med_ret5d": -0.976,
    "med_ret10d": -1.536
  },
  {
    "combo": "T2",
    "tier": "T2",
    "mod": "",
    "n_picks": 2233,
    "win5d": 42.68,
    "avg_ret5d": -0.098,
    "win10d": 43.13,
    "avg_ret10d": -0.124,
    "med_ret5d": -0.873,
    "med_ret10d": -1.276
  },
  {
    "combo": "T2+e",
    "tier": "T2",
    "mod": "e",
    "n_picks": 1974,
    "win5d": 42.76,
    "avg_ret5d": -0.048,
    "win10d": 43.36,
    "avg_ret10d": 0.013,
    "med_ret5d": -0.799,
    "med_ret10d": -1.17
  },
  {
    "combo": "T2+k",
    "tier": "T2",
    "mod": "k",
    "n_picks": 2029,
    "win5d": 42.19,
    "avg_ret5d": -0.152,
    "win10d": 43.08,
    "avg_ret10d": -0.206,
    "med_ret5d": -0.879,
    "med_ret10d": -1.254
  },
  {
    "combo": "T2+ek",
    "tier": "T2",
    "mod": "ek",
    "n_picks": 1844,
    "win5d": 42.25,
    "avg_ret5d": -0.107,
    "win10d": 43.11,
    "avg_ret10d": -0.113,
    "med_ret5d": -0.818,
    "med_ret10d": -1.205
  },
  {
    "combo": "T3",
    "tier": "T3",
    "mod": "",
    "n_picks": 942,
    "win5d": 41.72,
    "avg_ret5d": -0.385,
    "win10d": 43.74,
    "avg_ret10d": -0.459,
    "med_ret5d": -0.931,
    "med_ret10d": -1.052
  },
  {
    "combo": "T3+e",
    "tier": "T3",
    "mod": "e",
    "n_picks": 857,
    "win5d": 42.24,
    "avg_ret5d": -0.377,
    "win10d": 44.69,
    "avg_ret10d": -0.325,
    "med_ret5d": -0.787,
    "med_ret10d": -0.864
  },
  {
    "combo": "T3+k",
    "tier": "T3",
    "mod": "k",
    "n_picks": 880,
    "win5d": 42.16,
    "avg_ret5d": -0.278,
    "win10d": 43.98,
    "avg_ret10d": -0.325,
    "med_ret5d": -0.824,
    "med_ret10d": -0.935
  },
  {
    "combo": "T3+ek",
    "tier": "T3",
    "mod": "ek",
    "n_picks": 810,
    "win5d": 42.1,
    "avg_ret5d": -0.32,
    "win10d": 44.81,
    "avg_ret10d": -0.242,
    "med_ret5d": -0.787,
    "med_ret10d": -0.857
  },
  {
    "combo": "T4",
    "tier": "T4",
    "mod": "",
    "n_picks": 491,
    "win5d": 43.38,
    "avg_ret5d": -0.302,
    "win10d": 44.6,
    "avg_ret10d": -0.058,
    "med_ret5d": -0.757,
    "med_ret10d": -0.752
  },
  {
    "combo": "T4+e",
    "tier": "T4",
    "mod": "e",
    "n_picks": 452,
    "win5d": 43.58,
    "avg_ret5d": -0.425,
    "win10d": 44.47,
    "avg_ret10d": -0.135,
    "med_ret5d": -0.695,
    "med_ret10d": -0.663
  },
  {
    "combo": "T4+k",
    "tier": "T4",
    "mod": "k",
    "n_picks": 478,
    "win5d": 42.26,
    "avg_ret5d": -0.421,
    "win10d": 44.14,
    "avg_ret10d": -0.12,
    "med_ret5d": -0.838,
    "med_ret10d": -0.772
  },
  {
    "combo": "T4+ek",
    "tier": "T4",
    "mod": "ek",
    "n_picks": 446,
    "win5d": 43.05,
    "avg_ret5d": -0.475,
    "win10d": 44.17,
    "avg_ret10d": -0.162,
    "med_ret5d": -0.728,
    "med_ret10d": -0.701
  },
  {
    "combo": "T5",
    "tier": "T5",
    "mod": "",
    "n_picks": 99,
    "win5d": 44.44,
    "avg_ret5d": -0.228,
    "win10d": 48.48,
    "avg_ret10d": 0.217,
    "med_ret5d": -0.858,
    "med_ret10d": -0.347
  },
  {
    "combo": "T5+e",
    "tier": "T5",
    "mod": "e",
    "n_picks": 96,
    "win5d": 44.79,
    "avg_ret5d": -0.114,
    "win10d": 47.92,
    "avg_ret10d": 0.21,
    "med_ret5d": -0.784,
    "med_ret10d": -0.347
  },
  {
    "combo": "T5+k",
    "tier": "T5",
    "mod": "k",
    "n_picks": 99,
    "win5d": 44.44,
    "avg_ret5d": -0.228,
    "win10d": 48.48,
    "avg_ret10d": 0.217,
    "med_ret5d": -0.858,
    "med_ret10d": -0.347
  },
  {
    "combo": "T5+ek",
    "tier": "T5",
    "mod": "ek",
    "n_picks": 96,
    "win5d": 44.79,
    "avg_ret5d": -0.114,
    "win10d": 47.92,
    "avg_ret10d": 0.21,
    "med_ret5d": -0.784,
    "med_ret10d": -0.347
  }
]